greengen/__init__.py
greengen/api.py
greengen/generator.py
greengen-1.0.1.dist-info/METADATA
greengen-1.0.1.dist-info/WHEEL
greengen-1.0.1.dist-info/top_level.txt
greengen-1.0.1.dist-info/RECORD
