Metadata-Version: 2.1
Name: greengen
Version: 1.0.1
Summary: Nesting generators using greenlets
Home-page: https://github.com/guylapid/greengen
Author: guylapid
License: UNKNOWN
Platform: UNKNOWN
Classifier: Programming Language :: Python :: 2
Classifier: Programming Language :: Python :: 2.7
Classifier: Programming Language :: Python :: 3
Classifier: Programming Language :: Python :: 3.7
Requires-Dist: greenlet
Requires-Dist: decorator
